<?xml version="1.0" encoding="utf-8" ?>
<widget
    id="stoneworx.tagcloud.TagCloud"
    pluginWidget="true"
    needsEntityContext="true"
    offlineCapable="true"
    supportedPlatform="Web"
    xmlns="http://www.mendix.com/widget/1.0/"
    xmlns:xsi="http://www.w3.org/2001/XMLSchema-instance"
    xsi:schemaLocation="http://www.mendix.com/widget/1.0/ ../node_modules/mendix/custom_widget.xsd"
>
    <name>Tag Cloud</name>
    <description>
        Simple and extensible tag/word cloud React component based on https://www.npmjs.com/package/react-tagcloud
    </description>
    <icon />
    <properties>
        <propertyGroup caption="General">
            <property key="tagList" type="datasource" isList="true">
                <caption>Tag List</caption>
                <description>Data source providing Tag objects</description>
            </property>
            <property key="uniqueId" type="attribute" dataSource="tagList" required="false">
                <caption>Tag Key (Unique)</caption>
                <description>If it is not provided, value property will be used instead.</description>
                <attributeTypes>
                    <attributeType name="String" />
                </attributeTypes>
            </property>
            <property key="caption" type="attribute" dataSource="tagList">
                <caption>Caption</caption>
                <description>Caption</description>
                <attributeTypes>
                    <attributeType name="String" />
                </attributeTypes>
            </property>
            <property key="value" type="attribute" dataSource="tagList">
                <caption>Value</caption>
                <description>Value</description>
                <attributeTypes>
                    <attributeType name="Integer" />
                    <attributeType name="Decimal" />
                    <attributeType name="Long" />
                </attributeTypes>
            </property>
            <property key="color" type="attribute" dataSource="tagList" required="false">
                <caption>Color</caption>
                <description>Color of the tag. If not provided, random color will be used instead.</description>
                <attributeTypes>
                    <attributeType name="String" />
                </attributeTypes>
            </property>
            <!-- Action property -->

            <!-- Size property -->
            <property key="minSize" type="integer" defaultValue="12">
                <caption>Minimum Size</caption>
                <description>Minimal font size (in px) used in cloud.</description>
            </property>
            <property key="maxSize" type="integer" defaultValue="35">
                <caption>Maximum Size</caption>
                <description>Maximal font size (in px) used in cloud.</description>
            </property>
            <!-- (...) -->
            <property key="shuffle" type="boolean" defaultValue="true">
                <caption>Shuffle</caption>
                <description>If true, tags are shuffled. When tags are modified, cloud is re-shuffled.</description>
            </property>
            <property key="disableRandomColor" type="boolean" defaultValue="false">
                <caption>Disable Random Color</caption>
                <description>If true, random color is not used.</description>
            </property>
            <property key="randomSeed" type="integer" defaultValue="0">
                <caption>Random Seed</caption>
                <description>Random seed used to shuffle tags and generate color.</description>
            </property>
        </propertyGroup>
        <propertyGroup caption="Events">
            <property key="onClickAction" type="action">
                <caption>On Click</caption>
                <description>Action to be executed when a tag is clicked.</description>
                <actionVariables>
                    <actionVariable key="eventTagKey" type="String" caption="Tag Key" />
                </actionVariables>
            </property>
            <property key="onDoubleClickAction" type="action">
                <caption>On Double Click</caption>
                <description>Action to be executed when a tag is double-clicked.</description>
                <actionVariables>
                    <actionVariable key="eventTagKey" type="String" caption="Tag Key" />
                </actionVariables>
            </property>
            <property key="onMouseMoveAction" type="action">
                <caption>On Mouse Move</caption>
                <description>Action to be executed when mouse is moved over a tag.</description>
                <actionVariables>
                    <actionVariable key="eventTagKey" type="String" caption="Tag Key" />
                </actionVariables>
            </property>
        </propertyGroup>
    </properties>
</widget>
